Workbook

Sheet UR
A1: ID | B1: Versión | C1: Descripción del Requerimiento | D1: Prioridad | E1: Riesgo | F1: Dificultad | G1: Tipo | H1: Estado
A2: UR-01 | B2: 1.1 | C2: El sistema deberá proveer un servicio Store & Forward satelital, almacenando datos durante su orbita para ser descargados en una estación terrestre. | D2: Alta | E2: Alto | F2: Media | G2: Funcional | H2: Propuesto
A3: UR-02 | B3: 1.2 | C3: El sistema deberá soportar un enlace downlink desde el satélite hacia estaciones terrenas en territorio chileno. | D3: Alta | E3: Medio | F3: Baja | G3: Funcional | H3: Propuesto
A4: UR-03 | B4: 1.2 | C4: El sistema deberá soportar un enlace uplink desde estaciones remotas de monitoreo meteorológico, sismológico y/o vulcanológico hacia el satélite para la recolección de datos. | D4: Alta | E4: Medio | F4: Baja | G4: Funcional | H4: Propuesto
A5: UR-04 | B5: 1.2 | C5: El sistema deberá ser compatible con el estándar internacional para recolección de datos ambientales por satélite utilizado por estaciones remotas autónomas de meteorología, sismología, vulcanología, etc. | D5: Alta | E5: Medio | F5: Media | G5: Proceso | H5: Propuesto
A6: UR-05 | B6: 1.1 | C6: El sistema deberá asegurar la integridad de los datos durante su recepción, almacenamiento y transmisión. | D6: Media | E6: Bajo | F6: Baja | G6: Funcional | H6: Propuesto
A7: UR-06 | B7: 1.2 | C7: El sistema deberá ser compatible con plataforma CubeSat 12U en órbita terrestre baja (LEO) sol síncrona a una altitud nominal aproximada de 650 km con una inclinación de 96°. | D7: Alta | E7: Alto | F7: Baja | G7: No funcional | H7: Propuesto
A8: UR-07 | B8: 1.1 | C8: El sistema deberá cubrir el territorio chileno continental, zonas extremas, territorio insular y territorio antártico. | D8: Media | E8: Bajo | F8: Baja | G8: Funcional | H8: Propuesto
A9: UR-08 | B9: 1.2 | C9: El sistema deberá permitir el uso de componentes COTS siempre que cumplan con: (a) funcionamiento en órbita probada, (b) tolerancia a la radiación verificada, o (c) mitigaciones de diseño que reduzcan el riesgo a un nivel aceptable para la misión. | D9: Alta | E9: Alto | F9: Media | G9: No funcional | H9: Propuesto
A10: UR-09 | B10: 1.1 | C10: El sistema deberá ser de carácter experimental, con proyección a futuras aplicaciones comerciales. | D10: Baja | E10: Bajo | F10: Baja | G10: No funcional | H10: Propuesto
A11: UR-10 | B11: 1.1 | C11: El sistema deberá presentar una arquitectura modular, reutilizable y escalable. | D11: Baja | E11: Bajo | F11: Media | G11: No funcional | H11: Propuesto
A12: UR-11 | B12: 1.1 | C12: El sistema debe garantizar una vida útil operativa mínima de 5 años en el entorno de radiación LEO definido. | D12: Alta | E12: Alto | F12: Media | G12: No funcional | H12: Propuesto
A13: UR-12 | B13: 1.1 | C13: El sistema debe ser validado mediante pruebas funcionales en tierra y demostración en órbita. | D13: Baja | E13: Bajo | F13: Baja | G13: Proceso | H13: Propuesto
A14: UR-13 | B14: 1.0 | C14: El sistema deberá ser compatible con el sistema de separación del lanzador seleccionado EXOpod 12U, cumpliendo con las restricciones geométricas, mecánicas y de seguridad. | G14: No funcional | H14: Propuesto

Sheet SR
A1: ID | B1: Versión | C1: Descripción del Requerimiento | D1: Prioridad | E1: Riesgo | F1: Dificultad | G1: Tipo | H1: Estado
A2: SR-01 | B2: 1.2 | C2: El sistema deberá permitir la recepción de paquetes de datos con una tamaño desde 32 a 256 bits, con una tasa de datos de 400 bps. | D2: Alta | E2: Alto | F2: Media | G2: Funcional | H2: Propuesto
A3: SR-02 | B3: 1.4 | C3: El sistema deberá operar como receptor en el rango de frecuencias 401 - 403 MHz utilizado por estaciones remotas, con una polarización circular derecha y un ancho de haz de 130° HPBW. | D3: Alta | E3: Alto | F3: Media | G3: No funcional | H3: Propuesto
A4: SR-03 | B4: 1.3 | C4: El sistema deberá ser compatible con la estructura de datos enviado por las estaciones remotas , incluyendo modulación, canalización y protocolos, además de las variaciones en frecuencia por efecto Doppler. | D4: Alta | E4: Alto | F4: Media | G4: Funcional | H4: Propuesto
A5: SR-04 | B5: 1.3 | C5: El sistema deberá almacenar al menos 1.000.000 mensajes de durante un tiempo máximo de 15 órbitas y sin pérdidas hasta establecer contacto con una estación terrestre para la descarga. | D5: Media | E5: Medio | F5: Baja | G5: Funcional | H5: Propuesto
A6: SR-05 | B6: 1.2 | C6: El sistema deberá mantener la asociación temporal de los datos almacenados. | D6: Baja | E6: Bajo | F6: Baja | G6: Funcional | H6: Propuesto
A7: SR-06 | B7: 1.2 | C7: El sistema deberá permitir la descarga de al menos 10.000 mensajes almacenados hacia estaciones terrestres cuando exista conectividad disponible. | D7: Media | E7: Medio | F7: Baja | G7: Funcional | H7: Propuesto
A8: SR-07 | B8: 1.3 | C8: El sistema deberá entregar los datos al subsistema de comunicaciones de la plataforma (Transponder Banda S) para el enlace downlink. | D8: Media | E8: Medio | F8: Baja | G8: Proceso | H8: Propuesto
A9: SR-08 | B9: 1.2 | C9: El sistema deberá comunicarse con el OBC del CubeSat 12U mediante el bus definido por la plataforma (CANBUS), gestionando una tasa de transferencia de datos compatible y reportando periódicamente su estado operativo. | D9: Alta | E9: Alto | F9: Media | G9: No funcional | H9: Propuesto
A10: SR-09 | B10: 1.3 | C10: El sistema deberá operar bajo el control del OBC, escuchando activamente en las zonas definidas por la misión y transmitiendo únicamente cuando sea ordenado. | D10: Media | E10: Bajo | F10: Baja | G10: Funcional | H10: Propuesto
A11: SR-10 | B11: 1.2 | C11: El sistema deberá implementar mecanismos de integridad de datos en todas las etapas, con un error de bit menor a 0.01% y control de acceso a la descarga de datos por estaciones terrestres. | D11: Media | E11: Medio | F11: Baja | G11: Interfaz | H11: Propuesto
A12: SR-13 | B12: 1.2 | C12: El sistema deberá consumir un máximo de 10 W en operación nominal y ser alimentado por el sistema de potencia del satélite de forma continua. | D12: Alta | E12: Alto | F12: Media | G12: No funcional | H12: Propuesto
... A17: SR-18 | B17: 1.2 | C17: El sistema deberá certificarse mediante prueba térmo-vacio, mecánicas, EMI y eléctricas en las instalaciones de Centro Espacial Nacional y ser validado en órbita. | D17: Media | E17: Bajo | F17: Media | G17: Proceso | H17: Propuesto
A18: SR-19 | B18: 1.0 | C18: El sistema deberá ser respetar la envolvente interna permita, los volúmen prohibídos y las restricciones sobre protrusiones, mecanismos móviles y bordes activos, asegurando la integración con la plataforma. | G18: No funcional | H18: Propuesto
A19: SR-20 | B19: 1.0 | C19: El sistema deberá soportar los ambientes mecánicos de lanzamiento (cargas cuasiestáticas, vibración y shock) definidos por el lanzador y deployer seleccionados. | G19: No funcional | H19: Propuesto
A20: SR-21 | B20: 1.0 | C20: El sistema deberá implementar Watchdog Timers externos e independientes para reinicio ante eventos SEU/Latch-up. | G20: Funcional | H20: Propuesto
A21: SR-22 | B21: 1.0 | C21: Protección electrónica contra Single Event Latch-up (SEL) mediante limitación de corriente activa. | G21: No funcional | H21: Propuesto
A22: SR-23 | B22: 1.0 | C22: Los componentes y materiales no metálicos que uitlice el sistema deberán cumplir con un TML < 1.0% y un CVCM <0.1% | G22: No funcional | H22: Propuesto

Sheet TR
A1: ID UR | B1: ID SR | D1: Prioridad | E1: Riego | F1: Dificultad | G1: Tipos | H1: Estado
A2: UR-01 | B2: SR-04 | D2: Baja | E2: Bajo | F2: Baja | G2: Funcional | H2: Propuesto
A3: UR-01 | B3: SR-06 | D3: Media | E3: Medio | F3: Media | G3: No funcional | H3: En desarrollo
A4: UR-02 | B4: SR-03 | D4: Alta | E4: Alto | F4: Alta | G4: Proceso | H4: Pruebas
A5: UR-02 | B5: SR-07 | D5: ND | E5: ND | F5: ND | G5: Interfaz | H5: Terminado
A6: UR-03 | B6: SR-02
A7: UR-03 | B7: SR-03 | D7: Impacto | E7: Nivel
A8: UR-04 | B8: SR-01 | D8: Bajo | E8: 1
A9: UR-04 | B9: SR-02 | D9: Medio | E9: 2
A10: UR-04 | B10: SR-03 | D10: Alto | E10: 3
A11: UR-05 | B11: SR-04 | D11: ND | E11: 0
A12: UR-05 | B12: SR-05
A13: UR-05 | B13: SR-08
A14: UR-05 | B14: SR-10
A15: UR-06 | B15: SR-13
A16: UR-06 | B16: SR-14
A17: UR-06 | B17: SR-15
A18: UR-06 | B18: SR-16
A19: UR-06 | B19: SR-19
A20: UR-06 | B20: SR-20
A21: UR-07 | B21: SR-09
A22: UR-07 | B22: SR-10
A23: UR-08 | B23: SR-16
... A36: UR-13 | B36: SR-22

Sheet MT
B1: {=TRANSPOSE(Tabla_SR[ID])} -> SR-01 | C1: SR-02 | D1: SR-03 | E1: SR-04 | F1: SR-05 | G1: SR-06 | H1: SR-07 | I1: SR-08 | J1: SR-09 | K1: SR-10 | L1: SR-13 | M1: SR-14 | N1: SR-15 | O1: SR-16 | P1: SR-17 | Q1: SR-18 | R1: SR-19 | S1: SR-20 | T1: SR-21 | U1: SR-22 | V1: SR-23 | W1: Cobertura
A2: {=Tabla_UR[ID]} -> UR-01 | B2: =IF(COUNTIFS(TR!$A:$A,$A2,TR!$B:$B,B$1)>0,"X","") | C2: =IF(COUNTIFS(TR!$A:$A,$A2,TR!$B:$B,C$1)>0,"X","") | D2: =IF(COUNTIFS(TR!$A:$A,$A2,TR!$B:$B,D$1)>0,"X","") | E2: =IF(COUNTIFS(TR!$A:$A,$A2,TR!$B:$B,E$1)>0,"X","") -> X | F2: =IF(COUNTIFS(TR!$A:$A,$A2,TR!$B:$B,F$1)>0,"X","") | G2: =IF(COUNTIFS(TR!$A:$A,$A2,TR!$B:$B,G$1)>0,"X","") -> X | H2: =IF(COUNTIFS(TR!$A:$A,$A2,TR!$B:$B,H$1)>0,"X","") | I2: =IF(COUNTIFS(TR!$A:$A,$A2,TR!$B:$B,I$1)>0,"X","") | ... V2: =IF(COUNTIFS(TR!$A:$A,$A2,TR!$B:$B,V$1)>0,"X","") | W2: =IF(COUNTIF(B2:V2,"X")=0,"No cubierto","Cubierto") -> Cubierto | X2: {=Tabla_UR[ID]} -> UR-01 | Y2: {=Tabla_UR[Descripción del Requerimiento]} -> El sistema deberá proveer un servicio Store & Forward satelital, almacenando datos durante su orbita para ser descargados en una estación terrestre.
A3: UR-02 | B3: =IF(COUNTIFS(TR!$A:$A,$A3,TR!$B:$B,B$1)>0,"X","") | C3: =IF(COUNTIFS(TR!$A:$A,$A3,TR!$B:$B,C$1)>0,"X","") | D3: =IF(COUNTIFS(TR!$A:$A,$A3,TR!$B:$B,D$1)>0,"X","") -> X | E3: =IF(COUNTIFS(TR!$A:$A,$A3,TR!$B:$B,E$1)>0,"X","") | F3: =IF(COUNTIFS(TR!$A:$A,$A3,TR!$B:$B,F$1)>0,"X","") | G3: =IF(COUNTIFS(TR!$A:$A,$A3,TR!$B:$B,G$1)>0,"X","") | H3: =IF(COUNTIFS(TR!$A:$A,$A3,TR!$B:$B,H$1)>0,"X","") -> X | I3: =IF(COUNTIFS(TR!$A:$A,$A3,TR!$B:$B,I$1)>0,"X","") | ... V3: =IF(COUNTIFS(TR!$A:$A,$A3,TR!$B:$B,V$1)>0,"X","") | W3: =IF(COUNTIF(B3:V3,"X")=0,"No cubierto","Cubierto") -> Cubierto | X3: UR-02 | Y3: El sistema deberá soportar un enlace downlink desde el satélite hacia estaciones terrenas en territorio chileno.
A4: UR-03 | B4: =IF(COUNTIFS(TR!$A:$A,$A4,TR!$B:$B,B$1)>0,"X","") | C4: =IF(COUNTIFS(TR!$A:$A,$A4,TR!$B:$B,C$1)>0,"X","") -> X | D4: =IF(COUNTIFS(TR!$A:$A,$A4,TR!$B:$B,D$1)>0,"X","") -> X | E4: =IF(COUNTIFS(TR!$A:$A,$A4,TR!$B:$B,E$1)>0,"X","") | F4: =IF(COUNTIFS(TR!$A:$A,$A4,TR!$B:$B,F$1)>0,"X","") | G4: =IF(COUNTIFS(TR!$A:$A,$A4,TR!$B:$B,G$1)>0,"X","") | H4: =IF(COUNTIFS(TR!$A:$A,$A4,TR!$B:$B,H$1)>0,"X","") | I4: =IF(COUNTIFS(TR!$A:$A,$A4,TR!$B:$B,I$1)>0,"X","") | ... V4: =IF(COUNTIFS(TR!$A:$A,$A4,TR!$B:$B,V$1)>0,"X","") | W4: =IF(COUNTIF(B4:V4,"X")=0,"No cubierto","Cubierto") -> Cubierto | X4: UR-03 | Y4: El sistema deberá soportar un enlace uplink desde estaciones remotas de monitoreo meteorológico, sismológico y/o vulcanológico hacia el satélite para la recolección de datos.
A5: UR-04 | B5: =IF(COUNTIFS(TR!$A:$A,$A5,TR!$B:$B,B$1)>0,"X","") -> X | C5: =IF(COUNTIFS(TR!$A:$A,$A5,TR!$B:$B,C$1)>0,"X","") -> X | D5: =IF(COUNTIFS(TR!$A:$A,$A5,TR!$B:$B,D$1)>0,"X","") -> X | E5: =IF(COUNTIFS(TR!$A:$A,$A5,TR!$B:$B,E$1)>0,"X","") | F5: =IF(COUNTIFS(TR!$A:$A,$A5,TR!$B:$B,F$1)>0,"X","") | G5: =IF(COUNTIFS(TR!$A:$A,$A5,TR!$B:$B,G$1)>0,"X","") | H5: =IF(COUNTIFS(TR!$A:$A,$A5,TR!$B:$B,H$1)>0,"X","") | I5: =IF(COUNTIFS(TR!$A:$A,$A5,TR!$B:$B,I$1)>0,"X","") | ... V5: =IF(COUNTIFS(TR!$A:$A,$A5,TR!$B:$B,V$1)>0,"X","") | W5: =IF(COUNTIF(B5:V5,"X")=0,"No cubierto","Cubierto") -> Cubierto | X5: UR-04 | Y5: El sistema deberá ser compatible con el estándar internacional para recolección de datos ambientales por satélite utilizado por estaciones remotas autónomas de meteorología, sismología, vulcanología, etc.
A6: UR-05 | B6: =IF(COUNTIFS(TR!$A:$A,$A6,TR!$B:$B,B$1)>0,"X","") | C6: =IF(COUNTIFS(TR!$A:$A,$A6,TR!$B:$B,C$1)>0,"X","") | D6: =IF(COUNTIFS(TR!$A:$A,$A6,TR!$B:$B,D$1)>0,"X","") | E6: =IF(COUNTIFS(TR!$A:$A,$A6,TR!$B:$B,E$1)>0,"X","") -> X | F6: =IF(COUNTIFS(TR!$A:$A,$A6,TR!$B:$B,F$1)>0,"X","") -> X | G6: =IF(COUNTIFS(TR!$A:$A,$A6,TR!$B:$B,G$1)>0,"X","") | H6: =IF(COUNTIFS(TR!$A:$A,$A6,TR!$B:$B,H$1)>0,"X","") | I6: =IF(COUNTIFS(TR!$A:$A,$A6,TR!$B:$B,I$1)>0,"X","") -> X | ... V6: =IF(COUNTIFS(TR!$A:$A,$A6,TR!$B:$B,V$1)>0,"X","") | W6: =IF(COUNTIF(B6:V6,"X")=0,"No cubierto","Cubierto") -> Cubierto | X6: UR-05 | Y6: El sistema deberá asegurar la integridad de los datos durante su recepción, almacenamiento y transmisión.
A7: UR-06 | B7: =IF(COUNTIFS(TR!$A:$A,$A7,TR!$B:$B,B$1)>0,"X","") | C7: =IF(COUNTIFS(TR!$A:$A,$A7,TR!$B:$B,C$1)>0,"X","") | D7: =IF(COUNTIFS(TR!$A:$A,$A7,TR!$B:$B,D$1)>0,"X","") | E7: =IF(COUNTIFS(TR!$A:$A,$A7,TR!$B:$B,E$1)>0,"X","") | F7: =IF(COUNTIFS(TR!$A:$A,$A7,TR!$B:$B,F$1)>0,"X","") | G7: =IF(COUNTIFS(TR!$A:$A,$A7,TR!$B:$B,G$1)>0,"X","") | H7: =IF(COUNTIFS(TR!$A:$A,$A7,TR!$B:$B,H$1)>0,"X","") | I7: =IF(COUNTIFS(TR!$A:$A,$A7,TR!$B:$B,I$1)>0,"X","") | ... V7: =IF(COUNTIFS(TR!$A:$A,$A7,TR!$B:$B,V$1)>0,"X","") | W7: =IF(COUNTIF(B7:V7,"X")=0,"No cubierto","Cubierto") -> Cubierto | X7: UR-06 | Y7: El sistema deberá ser compatible con plataforma CubeSat 12U en órbita terrestre baja (LEO) sol síncrona a una altitud nominal aproximada de 650 km con una inclinación de 96°.
A8: UR-07 | B8: =IF(COUNTIFS(TR!$A:$A,$A8,TR!$B:$B,B$1)>0,"X","") | C8: =IF(COUNTIFS(TR!$A:$A,$A8,TR!$B:$B,C$1)>0,"X","") | D8: =IF(COUNTIFS(TR!$A:$A,$A8,TR!$B:$B,D$1)>0,"X","") | E8: =IF(COUNTIFS(TR!$A:$A,$A8,TR!$B:$B,E$1)>0,"X","") | F8: =IF(COUNTIFS(TR!$A:$A,$A8,TR!$B:$B,F$1)>0,"X","") | G8: =IF(COUNTIFS(TR!$A:$A,$A8,TR!$B:$B,G$1)>0,"X","") | H8: =IF(COUNTIFS(TR!$A:$A,$A8,TR!$B:$B,H$1)>0,"X","") | I8: =IF(COUNTIFS(TR!$A:$A,$A8,TR!$B:$B,I$1)>0,"X","") | ... V8: =IF(COUNTIFS(TR!$A:$A,$A8,TR!$B:$B,V$1)>0,"X","") | W8: =IF(COUNTIF(B8:V8,"X")=0,"No cubierto","Cubierto") -> Cubierto | X8: UR-07 | Y8: El sistema deberá cubrir el territorio chileno continental, zonas extremas, territorio insular y territorio antártico.
A9: UR-08 | B9: =IF(COUNTIFS(TR!$A:$A,$A9,TR!$B:$B,B$1)>0,"X","") | C9: =IF(COUNTIFS(TR!$A:$A,$A9,TR!$B:$B,C$1)>0,"X","") | D9: =IF(COUNTIFS(TR!$A:$A,$A9,TR!$B:$B,D$1)>0,"X","") | E9: =IF(COUNTIFS(TR!$A:$A,$A9,TR!$B:$B,E$1)>0,"X","") | F9: =IF(COUNTIFS(TR!$A:$A,$A9,TR!$B:$B,F$1)>0,"X","") | G9: =IF(COUNTIFS(TR!$A:$A,$A9,TR!$B:$B,G$1)>0,"X","") | H9: =IF(COUNTIFS(TR!$A:$A,$A9,TR!$B:$B,H$1)>0,"X","") | I9: =IF(COUNTIFS(TR!$A:$A,$A9,TR!$B:$B,I$1)>0,"X","") | ... V9: =IF(COUNTIFS(TR!$A:$A,$A9,TR!$B:$B,V$1)>0,"X","") -> X | W9: =IF(COUNTIF(B9:V9,"X")=0,"No cubierto","Cubierto") -> Cubierto | X9: UR-08 | Y9: El sistema deberá permitir el uso de componentes COTS siempre que cumplan con: (a) funcionamiento en órbita probada, (b) tolerancia a la radiación verificada, o (c) mitigaciones de diseño que reduzcan el riesgo a un nivel aceptable para la misión.
A10: UR-09 | B10: =IF(COUNTIFS(TR!$A:$A,$A10,TR!$B:$B,B$1)>0,"X","") | C10: =IF(COUNTIFS(TR!$A:$A,$A10,TR!$B:$B,C$1)>0,"X","") | D10: =IF(COUNTIFS(TR!$A:$A,$A10,TR!$B:$B,D$1)>0,"X","") | E10: =IF(COUNTIFS(TR!$A:$A,$A10,TR!$B:$B,E$1)>0,"X","") | F10: =IF(COUNTIFS(TR!$A:$A,$A10,TR!$B:$B,F$1)>0,"X","") | G10: =IF(COUNTIFS(TR!$A:$A,$A10,TR!$B:$B,G$1)>0,"X","") | H10: =IF(COUNTIFS(TR!$A:$A,$A10,TR!$B:$B,H$1)>0,"X","") | I10: =IF(COUNTIFS(TR!$A:$A,$A10,TR!$B:$B,I$1)>0,"X","") | ... V10: =IF(COUNTIFS(TR!$A:$A,$A10,TR!$B:$B,V$1)>0,"X","") | W10: =IF(COUNTIF(B10:V10,"X")=0,"No cubierto","Cubierto") -> Cubierto | X10: UR-09 | Y10: El sistema deberá ser de carácter experimental, con proyección a futuras aplicaciones comerciales.
A11: UR-10 | B11: =IF(COUNTIFS(TR!$A:$A,$A11,TR!$B:$B,B$1)>0,"X","") | C11: =IF(COUNTIFS(TR!$A:$A,$A11,TR!$B:$B,C$1)>0,"X","") | D11: =IF(COUNTIFS(TR!$A:$A,$A11,TR!$B:$B,D$1)>0,"X","") | E11: =IF(COUNTIFS(TR!$A:$A,$A11,TR!$B:$B,E$1)>0,"X","") | F11: =IF(COUNTIFS(TR!$A:$A,$A11,TR!$B:$B,F$1)>0,"X","") | G11: =IF(COUNTIFS(TR!$A:$A,$A11,TR!$B:$B,G$1)>0,"X","") | H11: =IF(COUNTIFS(TR!$A:$A,$A11,TR!$B:$B,H$1)>0,"X","") | I11: =IF(COUNTIFS(TR!$A:$A,$A11,TR!$B:$B,I$1)>0,"X","") | ... V11: =IF(COUNTIFS(TR!$A:$A,$A11,TR!$B:$B,V$1)>0,"X","") | W11: =IF(COUNTIF(B11:V11,"X")=0,"No cubierto","Cubierto") -> Cubierto | X11: UR-10 | Y11: El sistema deberá presentar una arquitectura modular, reutilizable y escalable.
A12: UR-11 | B12: =IF(COUNTIFS(TR!$A:$A,$A12,TR!$B:$B,B$1)>0,"X","") | C12: =IF(COUNTIFS(TR!$A:$A,$A12,TR!$B:$B,C$1)>0,"X","") | D12: =IF(COUNTIFS(TR!$A:$A,$A12,TR!$B:$B,D$1)>0,"X","") | E12: =IF(COUNTIFS(TR!$A:$A,$A12,TR!$B:$B,E$1)>0,"X","") | F12: =IF(COUNTIFS(TR!$A:$A,$A12,TR!$B:$B,F$1)>0,"X","") | G12: =IF(COUNTIFS(TR!$A:$A,$A12,TR!$B:$B,G$1)>0,"X","") | H12: =IF(COUNTIFS(TR!$A:$A,$A12,TR!$B:$B,H$1)>0,"X","") | I12: =IF(COUNTIFS(TR!$A:$A,$A12,TR!$B:$B,I$1)>0,"X","") | ... V12: =IF(COUNTIFS(TR!$A:$A,$A12,TR!$B:$B,V$1)>0,"X","") -> X | W12: =IF(COUNTIF(B12:V12,"X")=0,"No cubierto","Cubierto") -> Cubierto | X12: UR-11 | Y12: El sistema debe garantizar una vida útil operativa mínima de 5 años en el entorno de radiación LEO definido.
A13: UR-12 | B13: =IF(COUNTIFS(TR!$A:$A,$A13,TR!$B:$B,B$1)>0,"X","") | C13: =IF(COUNTIFS(TR!$A:$A,$A13,TR!$B:$B,C$1)>0,"X","") | D13: =IF(COUNTIFS(TR!$A:$A,$A13,TR!$B:$B,D$1)>0,"X","") | E13: =IF(COUNTIFS(TR!$A:$A,$A13,TR!$B:$B,E$1)>0,"X","") | F13: =IF(COUNTIFS(TR!$A:$A,$A13,TR!$B:$B,F$1)>0,"X","") | G13: =IF(COUNTIFS(TR!$A:$A,$A13,TR!$B:$B,G$1)>0,"X","") | H13: =IF(COUNTIFS(TR!$A:$A,$A13,TR!$B:$B,H$1)>0,"X","") | I13: =IF(COUNTIFS(TR!$A:$A,$A13,TR!$B:$B,I$1)>0,"X","") | ... V13: =IF(COUNTIFS(TR!$A:$A,$A13,TR!$B:$B,V$1)>0,"X","") | W13: =IF(COUNTIF(B13:V13,"X")=0,"No cubierto","Cubierto") -> Cubierto | X13: UR-12 | Y13: El sistema debe ser validado mediante pruebas funcionales en tierra y demostración en órbita.
A14: UR-13 | B14: =IF(COUNTIFS(TR!$A:$A,$A14,TR!$B:$B,B$1)>0,"X","") | C14: =IF(COUNTIFS(TR!$A:$A,$A14,TR!$B:$B,C$1)>0,"X","") | D14: =IF(COUNTIFS(TR!$A:$A,$A14,TR!$B:$B,D$1)>0,"X","") | E14: =IF(COUNTIFS(TR!$A:$A,$A14,TR!$B:$B,E$1)>0,"X","") | F14: =IF(COUNTIFS(TR!$A:$A,$A14,TR!$B:$B,F$1)>0,"X","") | G14: =IF(COUNTIFS(TR!$A:$A,$A14,TR!$B:$B,G$1)>0,"X","") | H14: =IF(COUNTIFS(TR!$A:$A,$A14,TR!$B:$B,H$1)>0,"X","") | I14: =IF(COUNTIFS(TR!$A:$A,$A14,TR!$B:$B,I$1)>0,"X","") | ... V14: =IF(COUNTIFS(TR!$A:$A,$A14,TR!$B:$B,V$1)>0,"X","") | W14: =IF(COUNTIF(B14:V14,"X")=0,"No cubierto","Cubierto") -> Cubierto | X14: UR-13 | Y14: El sistema deberá ser compatible con el sistema de separación del lanzador seleccionado EXOpod 12U, cumpliendo con las restricciones geométricas, mecánicas y de seguridad.
X18: {=Tabla_SR[ID]} -> SR-01 | Y18: {=Tabla_SR[Descripción del Requerimiento]} -> El sistema deberá permitir la recepción de paquetes de datos con una tamaño desde 32 a 256 bits, con una tasa de datos de 400 bps.
X19: SR-02 | Y19: El sistema deberá operar como receptor en el rango de frecuencias 401 - 403 MHz utilizado por estaciones remotas, con una polarización circular derecha y un ancho de haz de 130° HPBW.
X20: SR-03 | Y20: El sistema deberá ser compatible con la estructura de datos enviado por las estaciones remotas , incluyendo modulación, canalización y protocolos, además de las variaciones en frecuencia por efecto Doppler.
X21: SR-04 | Y21: El sistema deberá almacenar al menos 1.000.000 mensajes de durante un tiempo máximo de 15 órbitas y sin pérdidas hasta establecer contacto con una estación terrestre para la descarga.
X22: SR-05 | Y22: El sistema deberá mantener la asociación temporal de los datos almacenados.
X23: SR-06 | Y23: El sistema deberá permitir la descarga de al menos 10.000 mensajes almacenados hacia estaciones terrestres cuando exista conectividad disponible.
X24: SR-07 | Y24: El sistema deberá entregar los datos al subsistema de comunicaciones de la plataforma (Transponder Banda S) para el enlace downlink.
X25: SR-08 | Y25: El sistema deberá comunicarse con el OBC del CubeSat 12U mediante el bus definido por la plataforma (CANBUS), gestionando una tasa de transferencia de datos compatible y reportando periódicamente su estado operativo.
X26: SR-09 | Y26: El sistema deberá operar bajo el control del OBC, escuchando activamente en las zonas definidas por la misión y transmitiendo únicamente cuando sea ordenado.
X27: SR-10 | Y27: El sistema deberá implementar mecanismos de integridad de datos en todas las etapas, con un error de bit menor a 0.01% y control de acceso a la descarga de datos por estaciones terrestres.
X28: SR-13 | Y28: El sistema deberá consumir un máximo de 10 W en operación nominal y ser alimentado por el sistema de potencia del satélite de forma continua.
X29: SR-14 | Y29: El sistema deberá tener dimensiones máximas 20 cm x 20 cm x 10 cm.
X30: SR-15 | Y30: El sistema deberá tener una masa máxima de 3.0 kg y mantener su Centro de Gravedad (CoG) a ±2 mm del centro geométrico, el cual coincide con el eje logitudinal geométrico del satélite.
... X38: SR-23 | Y38: Los componentes y materiales no metálicos que uitlice el sistema deberán cumplir con un TML < 1.0% y un CVCM <0.1%

Sheet RISK
A1: ID | B1: Descripción | C1: Impacto | D1: Probabilidad (%) | E1: Nivel Impacto | F1: Nivel Probabilidad | G1: Valor Riesgo | H1: Clasificación | I1: Mitigación Propuesta | K1: ID | L1: Descripción | M1: Impacto | N1: Probabilidad (%) | O1: Nivel Impacto | P1: Nivel Probabilidad | Q1: Valor Riesgo | R1: Clasificación | S1: Mitigación Propuesta
A2: =Tabla_UR[[#This Row],[ID]] -> UR-01 | B2: =Tabla_UR[[#This Row],[Descripción del Requerimiento]] -> El sistema deberá proveer un servicio Store & Forward satelital, almacenando datos durante su orbita para ser descargados en una estación terrestre. | C2: =Tabla_UR[[#This Row],[Riesgo]] -> Alto | D2: 20 | E2: =_xlfn.XLOOKUP(C2, Tabla5[Impacto], Tabla5[Nivel]) -> 3 | F2: =IF(D2<=10,1, IF(D2<=30,2,3)) -> 2 | G2: =Tabla7[[#This Row],[Nivel Impacto]]*Tabla7[[#This Row],[Nivel Probabilidad]] -> 6 | H2: =IF(G2>=6,"Alto", IF(G2>=3,"Medio","Bajo")) -> Alto | I2: Diseño de memoria no volátil con margen ≥50%, simulación de carga orbital y pruebas de estrés en tierra | K2: =Tabla_SR[[#This Row],[ID]] -> SR-01 | L2: =Tabla_SR[[#This Row],[Descripción del Requerimiento]] -> El sistema deberá permitir la recepción de paquetes de datos con una tamaño desde 32 a 256 bits, con una tasa de datos de 400 bps. | M2: =Tabla_SR[[#This Row],[Riesgo]] -> Alto | N2: 15 | O2: =_xlfn.XLOOKUP(M2, Tabla5[Impacto], Tabla5[Nivel]) -> 3 | P2: =IF(N2<=10,1, IF(N2<=30,2,3)) -> 2 | Q2: =Tabla710[[#This Row],[Nivel Impacto]]*Tabla710[[#This Row],[Nivel Probabilidad]] -> 6 | R2: =IF(Q2>=6,"Alto", IF(Q2>=3,"Medio","Bajo")) -> Alto | S2: Prototipo temprano del receptor y pruebas BER en laboratorio
A3: =Tabla_UR[[#This Row],[ID]] -> UR-02 | B3: =Tabla_UR[[#This Row],[Descripción del Requerimiento]] -> El sistema deberá soportar un enlace downlink desde el satélite hacia estaciones terrenas en territorio chileno. | C3: =Tabla_UR[[#This Row],[Riesgo]] -> Medio | D3: 10 | E3: =_xlfn.XLOOKUP(C3, Tabla5[Impacto], Tabla5[Nivel]) -> 2 | F3: =IF(D3<=10,1, IF(D3<=30,2,3)) -> 1 | G3: =Tabla7[[#This Row],[Nivel Impacto]]*Tabla7[[#This Row],[Nivel Probabilidad]] -> 2 | H3: =IF(G3>=6,"Alto", IF(G3>=3,"Medio","Bajo")) -> Bajo | K3: =Tabla_SR[[#This Row],[ID]] -> SR-02 | L3: =Tabla_SR[[#This Row],[Descripción del Requerimiento]] -> El sistema deberá operar como receptor en el rango de frecuencias 401 - 403 MHz utilizado por estaciones remotas, con una polarización circular derecha y un ancho de haz de 130° HPBW. | M3: =Tabla_SR[[#This Row],[Riesgo]] -> Alto | N3: 10 | O3: =_xlfn.XLOOKUP(M3, Tabla5[Impacto], Tabla5[Nivel]) -> 3 | P3: =IF(N3<=10,1, IF(N3<=30,2,3)) -> 1 | Q3: =Tabla710[[#This Row],[Nivel Impacto]]*Tabla710[[#This Row],[Nivel Probabilidad]] -> 3 | R3: =IF(Q3>=6,"Alto", IF(Q3>=3,"Medio","Bajo")) -> Medio | S3: Verificación de front-end RF y filtros certificados
A4: =Tabla_UR[[#This Row],[ID]] -> UR-03 | B4: =Tabla_UR[[#This Row],[Descripción del Requerimiento]] -> El sistema deberá soportar un enlace uplink desde estaciones remotas de monitoreo meteorológico, sismológico y/o vulcanológico hacia el satélite para la recolección de datos. | C4: =Tabla_UR[[#This Row],[Riesgo]] -> Medio | D4: 15 | E4: =_xlfn.XLOOKUP(C4, Tabla5[Impacto], Tabla5[Nivel]) -> 2 | F4: =IF(D4<=10,1, IF(D4<=30,2,3)) -> 2 | G4: =Tabla7[[#This Row],[Nivel Impacto]]*Tabla7[[#This Row],[Nivel Probabilidad]] -> 4 | H4: =IF(G4>=6,"Alto", IF(G4>=3,"Medio","Bajo")) -> Medio | I4: Validación temprana con transmisores representativos y pruebas HIL | K4: =Tabla_SR[[#This Row],[ID]] -> SR-03 | L4: =Tabla_SR[[#This Row],[Descripción del Requerimiento]] -> El sistema deberá ser compatible con la estructura de datos enviado por las estaciones remotas , incluyendo modulación, canalización y protocolos, además de las variaciones en frecuencia por efecto Doppler. | M4: =Tabla_SR[[#This Row],[Riesgo]] -> Alto | N4: 25 | O4: =_xlfn.XLOOKUP(M4, Tabla5[Impacto], Tabla5[Nivel]) -> 3 | P4: =IF(N4<=10,1, IF(N4<=30,2,3)) -> 2 | Q4: =Tabla710[[#This Row],[Nivel Impacto]]*Tabla710[[#This Row],[Nivel Probabilidad]] -> 6 | R4: =IF(Q4>=6,"Alto", IF(Q4>=3,"Medio","Bajo")) -> Alto | S4: Simulación Doppler y pruebas con generador de señales
A5: =Tabla_UR[[#This Row],[ID]] -> UR-04 | B5: =Tabla_UR[[#This Row],[Descripción del Requerimiento]] -> El sistema deberá ser compatible con el estándar internacional para recolección de datos ambientales por satélite utilizado por estaciones remotas autónomas de meteorología, sismología, vulcanología, etc. | C5: =Tabla_UR[[#This Row],[Riesgo]] -> Medio | D5: 20 | E5: =_xlfn.XLOOKUP(C5, Tabla5[Impacto], Tabla5[Nivel]) -> 2 | F5: =IF(D5<=10,1, IF(D5<=30,2,3)) -> 2 | G5: =Tabla7[[#This Row],[Nivel Impacto]]*Tabla7[[#This Row],[Nivel Probabilidad]] -> 4 | H5: =IF(G5>=6,"Alto", IF(G5>=3,"Medio","Bajo")) -> Medio | I5: Revisión de estándar ARGOS y asesoría INVAP | K5: =Tabla_SR[[#This Row],[ID]] -> SR-04 | L5: =Tabla_SR[[#This Row],[Descripción del Requerimiento]] -> El sistema deberá almacenar al menos 1.000.000 mensajes de durante un tiempo máximo de 15 órbitas y sin pérdidas hasta establecer contacto con una estación terrestre para la descarga. | M5: =Tabla_SR[[#This Row],[Riesgo]] -> Medio | N5: 20 | O5: =_xlfn.XLOOKUP(M5, Tabla5[Impacto], Tabla5[Nivel]) -> 2 | P5: =IF(N5<=10,1, IF(N5<=30,2,3)) -> 2 | Q5: =Tabla710[[#This Row],[Nivel Impacto]]*Tabla710[[#This Row],[Nivel Probabilidad]] -> 4 | R5: =IF(Q5>=6,"Alto", IF(Q5>=3,"Medio","Bajo")) -> Medio | S5: Margen de memoria ≥50% y control de overflow
A6: =Tabla_UR[[#This Row],[ID]] -> UR-05 | B6: =Tabla_UR[[#This Row],[Descripción del Requerimiento]] -> El sistema deberá asegurar la integridad de los datos durante su recepción, almacenamiento y transmisión. | C6: =Tabla_UR[[#This Row],[Riesgo]] -> Bajo | D6: 10 | E6: =_xlfn.XLOOKUP(C6, Tabla5[Impacto], Tabla5[Nivel]) -> 1 | F6: =IF(D6<=10,1, IF(D6<=30,2,3)) -> 1 | G6: =Tabla7[[#This Row],[Nivel Impacto]]*Tabla7[[#This Row],[Nivel Probabilidad]] -> 1 | H6: =IF(G6>=6,"Alto", IF(G6>=3,"Medio","Bajo")) -> Bajo | K6: =Tabla_SR[[#This Row],[ID]] -> SR-05 | L6: =Tabla_SR[[#This Row],[Descripción del Requerimiento]] -> El sistema deberá mantener la asociación temporal de los datos almacenados. | M6: =Tabla_SR[[#This Row],[Riesgo]] -> Bajo | N6: 10 | O6: =_xlfn.XLOOKUP(M6, Tabla5[Impacto], Tabla5[Nivel]) -> 1 | P6: =IF(N6<=10,1, IF(N6<=30,2,3)) -> 1 | Q6: =Tabla710[[#This Row],[Nivel Impacto]]*Tabla710[[#This Row],[Nivel Probabilidad]] -> 1 | R6: =IF(Q6>=6,"Alto", IF(Q6>=3,"Medio","Bajo")) -> Bajo
A7: =Tabla_UR[[#This Row],[ID]] -> UR-06 | B7: =Tabla_UR[[#This Row],[Descripción del Requerimiento]] -> El sistema deberá ser compatible con plataforma CubeSat 12U en órbita terrestre baja (LEO) sol síncrona a una altitud nominal aproximada de 650 km con una inclinación de 96°. | C7: =Tabla_UR[[#This Row],[Riesgo]] -> Alto | D7: 15 | E7: =_xlfn.XLOOKUP(C7, Tabla5[Impacto], Tabla5[Nivel]) -> 3 | F7: =IF(D7<=10,1, IF(D7<=30,2,3)) -> 2 | G7: =Tabla7[[#This Row],[Nivel Impacto]]*Tabla7[[#This Row],[Nivel Probabilidad]] -> 6 | H7: =IF(G7>=6,"Alto", IF(G7>=3,"Medio","Bajo")) -> Alto | I7: Análisis de interfaces mecánicas/eléctricas y revisión PDR con proveedor de plataforma | K7: =Tabla_SR[[#This Row],[ID]] -> SR-06 | L7: =Tabla_SR[[#This Row],[Descripción del Requerimiento]] -> El sistema deberá permitir la descarga de al menos 10.000 mensajes almacenados hacia estaciones terrestres cuando exista conectividad disponible. | M7: =Tabla_SR[[#This Row],[Riesgo]] -> Medio | N7: 15 | O7: =_xlfn.XLOOKUP(M7, Tabla5[Impacto], Tabla5[Nivel]) -> 2 | P7: =IF(N7<=10,1, IF(N7<=30,2,3)) -> 2 | Q7: =Tabla710[[#This Row],[Nivel Impacto]]*Tabla710[[#This Row],[Nivel Probabilidad]] -> 4 | R7: =IF(Q7>=6,"Alto", IF(Q7>=3,"Medio","Bajo")) -> Medio | S7: Ensayos de descarga en peor escenario
A8: =Tabla_UR[[#This Row],[ID]] -> UR-07 | B8: =Tabla_UR[[#This Row],[Descripción del Requerimiento]] -> El sistema deberá cubrir el territorio chileno continental, zonas extremas, territorio insular y territorio antártico. | C8: =Tabla_UR[[#This Row],[Riesgo]] -> Bajo | D8: 5 | E8: =_xlfn.XLOOKUP(C8, Tabla5[Impacto], Tabla5[Nivel]) -> 1 | F8: =IF(D8<=10,1, IF(D8<=30,2,3)) -> 1 | G8: =Tabla7[[#This Row],[Nivel Impacto]]*Tabla7[[#This Row],[Nivel Probabilidad]] -> 1 | H8: =IF(G8>=6,"Alto", IF(G8>=3,"Medio","Bajo")) -> Bajo | K8: =Tabla_SR[[#This Row],[ID]] -> SR-07 | L8: =Tabla_SR[[#This Row],[Descripción del Requerimiento]] -> El sistema deberá entregar los datos al subsistema de comunicaciones de la plataforma (Transponder Banda S) para el enlace downlink. | M8: =Tabla_SR[[#This Row],[Riesgo]] -> Medio | N8: 10 | O8: =_xlfn.XLOOKUP(M8, Tabla5[Impacto], Tabla5[Nivel]) -> 2 | P8: =IF(N8<=10,1, IF(N8<=30,2,3)) -> 1 | Q8: =Tabla710[[#This Row],[Nivel Impacto]]*Tabla710[[#This Row],[Nivel Probabilidad]] -> 2 | R8: =IF(Q8>=6,"Alto", IF(Q8>=3,"Medio","Bajo")) -> Bajo
A9: =Tabla_UR[[#This Row],[ID]] -> UR-08 | B9: =Tabla_UR[[#This Row],[Descripción del Requerimiento]] -> El sistema deberá permitir el uso de componentes COTS siempre que cumplan con: (a) funcionamiento en órbita probada, (b) tolerancia a la radiación verificada, o (c) mitigaciones de diseño que reduzcan el riesgo a un nivel aceptable para la misión. | C9: =Tabla_UR[[#This Row],[Riesgo]] -> Alto | D9: 25 | E9: =_xlfn.XLOOKUP(C9, Tabla5[Impacto], Tabla5[Nivel]) -> 3 | F9: =IF(D9<=10,1, IF(D9<=30,2,3)) -> 2 | G9: =Tabla7[[#This Row],[Nivel Impacto]]*Tabla7[[#This Row],[Nivel Probabilidad]] -> 6 | H9: =IF(G9>=6,"Alto", IF(G9>=3,"Medio","Bajo")) -> Alto | I9: Selección COTS con validación espacial y mitigación por redundancia y watchdogs | K9: =Tabla_SR[[#This Row],[ID]] -> SR-08 | L9: =Tabla_SR[[#This Row],[Descripción del Requerimiento]] -> El sistema deberá comunicarse con el OBC del CubeSat 12U mediante el bus definido por la plataforma (CANBUS), gestionando una tasa de transferencia de datos compatible y reportando periódicamente su estado operativo. | M9: =Tabla_SR[[#This Row],[Riesgo]] -> Alto | N9: 25 | O9: =_xlfn.XLOOKUP(M9, Tabla5[Impacto], Tabla5[Nivel]) -> 3 | P9: =IF(N9<=10,1, IF(N9<=30,2,3)) -> 2 | Q9: =Tabla710[[#This Row],[Nivel Impacto]]*Tabla710[[#This Row],[Nivel Probabilidad]] -> 6 | R9: =IF(Q9>=6,"Alto", IF(Q9>=3,"Medio","Bajo")) -> Alto
A10: =Tabla_UR[[#This Row],[ID]] -> UR-09 | B10: =Tabla_UR[[#This Row],[Descripción del Requerimiento]] -> El sistema deberá ser de carácter experimental, con proyección a futuras aplicaciones comerciales. | C10: =Tabla_UR[[#This Row],[Riesgo]] -> Bajo | D10: 10 | E10: =_xlfn.XLOOKUP(C10, Tabla5[Impacto], Tabla5[Nivel]) -> 1 | F10: =IF(D10<=10,1, IF(D10<=30,2,3)) -> 1 | G10: =Tabla7[[#This Row],[Nivel Impacto]]*Tabla7[[#This Row],[Nivel Probabilidad]] -> 1 | H10: =IF(G10>=6,"Alto", IF(G10>=3,"Medio","Bajo")) -> Bajo | K10: =Tabla_SR[[#This Row],[ID]] -> SR-09 | L10: =Tabla_SR[[#This Row],[Descripción del Requerimiento]] -> El sistema deberá operar bajo el control del OBC, escuchando activamente en las zonas definidas por la misión y transmitiendo únicamente cuando sea ordenado. | M10: =Tabla_SR[[#This Row],[Riesgo]] -> Bajo | N10: 10 | O10: =_xlfn.XLOOKUP(M10, Tabla5[Impacto], Tabla5[Nivel]) -> 1 | P10: =IF(N10<=10,1, IF(N10<=30,2,3)) -> 1 | Q10: =Tabla710[[#This Row],[Nivel Impacto]]*Tabla710[[#This Row],[Nivel Probabilidad]] -> 1 | R10: =IF(Q10>=6,"Alto", IF(Q10>=3,"Medio","Bajo")) -> Bajo
A11: =Tabla_UR[[#This Row],[ID]] -> UR-10 | B11: =Tabla_UR[[#This Row],[Descripción del Requerimiento]] -> El sistema deberá presentar una arquitectura modular, reutilizable y escalable. | C11: =Tabla_UR[[#This Row],[Riesgo]] -> Bajo | D11: 10 | E11: =_xlfn.XLOOKUP(C11, Tabla5[Impacto], Tabla5[Nivel]) -> 1 | F11: =IF(D11<=10,1, IF(D11<=30,2,3)) -> 1 | G11: =Tabla7[[#This Row],[Nivel Impacto]]*Tabla7[[#This Row],[Nivel Probabilidad]] -> 1 | H11: =IF(G11>=6,"Alto", IF(G11>=3,"Medio","Bajo")) -> Bajo | K11: =Tabla_SR[[#This Row],[ID]] -> SR-10 | L11: =Tabla_SR[[#This Row],[Descripción del Requerimiento]] -> El sistema deberá implementar mecanismos de integridad de datos en todas las etapas, con un error de bit menor a 0.01% y control de acceso a la descarga de datos por estaciones terrestres. | M11: =Tabla_SR[[#This Row],[Riesgo]] -> Medio | N11: 20 | O11: =_xlfn.XLOOKUP(M11, Tabla5[Impacto], Tabla5[Nivel]) -> 2 | P11: =IF(N11<=10,1, IF(N11<=30,2,3)) -> 2 | Q11: =Tabla710[[#This Row],[Nivel Impacto]]*Tabla710[[#This Row],[Nivel Probabilidad]] -> 4 | R11: =IF(Q11>=6,"Alto", IF(Q11>=3,"Medio","Bajo")) -> Medio | S11: CRC, ACK/NACK y control de acceso
A12: =Tabla_UR[[#This Row],[ID]] -> UR-11 | B12: =Tabla_UR[[#This Row],[Descripción del Requerimiento]] -> El sistema debe garantizar una vida útil operativa mínima de 5 años en el entorno de radiación LEO definido. | C12: =Tabla_UR[[#This Row],[Riesgo]] -> Alto | D12: 30 | E12: =_xlfn.XLOOKUP(C12, Tabla5[Impacto], Tabla5[Nivel]) -> 3 | F12: =IF(D12<=10,1, IF(D12<=30,2,3)) -> 2 | G12: =Tabla7[[#This Row],[Nivel Impacto]]*Tabla7[[#This Row],[Nivel Probabilidad]] -> 6 | H12: =IF(G12>=6,"Alto", IF(G12>=3,"Medio","Bajo")) -> Alto | I12: Pruebas de estrés, análisis térmico y pruebas de vida aceleradas | K12: =Tabla_SR[[#This Row],[ID]] -> SR-13 | L12: =Tabla_SR[[#This Row],[Descripción del Requerimiento]] -> El sistema deberá consumir un máximo de 10 W en operación nominal y ser alimentado por el sistema de potencia del satélite de forma continua. | M12: =Tabla_SR[[#This Row],[Riesgo]] -> Alto | N12: 20 | O12: =_xlfn.XLOOKUP(M12, Tabla5[Impacto], Tabla5[Nivel]) -> 3 | P12: =IF(N12<=10,1, IF(N12<=30,2,3)) -> 2 | Q12: =Tabla710[[#This Row],[Nivel Impacto]]*Tabla710[[#This Row],[Nivel Probabilidad]] -> 6 | R12: =IF(Q12>=6,"Alto", IF(Q12>=3,"Medio","Bajo")) -> Alto | S12: Pruebas de compatibilidad CAN con OBC real
A13: =Tabla_UR[[#This Row],[ID]] -> UR-12 | B13: =Tabla_UR[[#This Row],[Descripción del Requerimiento]] -> El sistema debe ser validado mediante pruebas funcionales en tierra y demostración en órbita. | C13: =Tabla_UR[[#This Row],[Riesgo]] -> Bajo | D13: 10 | E13: =_xlfn.XLOOKUP(C13, Tabla5[Impacto], Tabla5[Nivel]) -> 1 | F13: =IF(D13<=10,1, IF(D13<=30,2,3)) -> 1 | G13: =Tabla7[[#This Row],[Nivel Impacto]]*Tabla7[[#This Row],[Nivel Probabilidad]] -> 1 | H13: =IF(G13>=6,"Alto", IF(G13>=3,"Medio","Bajo")) -> Bajo | K13: =Tabla_SR[[#This Row],[ID]] -> SR-14 | L13: =Tabla_SR[[#This Row],[Descripción del Requerimiento]] -> El sistema deberá tener dimensiones máximas 20 cm x 20 cm x 10 cm. | M13: =Tabla_SR[[#This Row],[Riesgo]] -> Alto | N13: 15 | O13: =_xlfn.XLOOKUP(M13, Tabla5[Impacto], Tabla5[Nivel]) -> 3 | P13: =IF(N13<=10,1, IF(N13<=30,2,3)) -> 2 | Q13: =Tabla710[[#This Row],[Nivel Impacto]]*Tabla710[[#This Row],[Nivel Probabilidad]] -> 6 | R13: =IF(Q13>=6,"Alto", IF(Q13>=3,"Medio","Bajo")) -> Alto | S13: Validación de lógica de estados y temporización
A14: =Tabla_UR[[#This Row],[ID]] -> UR-13 | C14: =Tabla_UR[[#This Row],[Riesgo]] -> 0 | E14: =_xlfn.XLOOKUP(C14, Tabla5[Impacto], Tabla5[Nivel]) -> #N/A | F14: =IF(D14<=10,1, IF(D14<=30,2,3)) -> 1 | G14: =Tabla7[[#This Row],[Nivel Impacto]]*Tabla7[[#This Row],[Nivel Probabilidad]] -> #N/A | H14: =IF(G14>=6,"Alto", IF(G14>=3,"Medio","Bajo")) -> #N/A | K14: =Tabla_SR[[#This Row],[ID]] -> SR-15 | L14: =Tabla_SR[[#This Row],[Descripción del Requerimiento]] -> El sistema deberá tener una masa máxima de 3.0 kg y mantener su Centro de Gravedad (CoG) a ±2 mm del centro geométrico, el cual coincide con el eje logitudinal geométrico del satélite. | M14: =Tabla_SR[[#This Row],[Riesgo]] -> Alto | N14: 30 | O14: =_xlfn.XLOOKUP(M14, Tabla5[Impacto], Tabla5[Nivel]) -> 3 | P14: =IF(N14<=10,1, IF(N14<=30,2,3)) -> 2 | Q14: =Tabla710[[#This Row],[Nivel Impacto]]*Tabla710[[#This Row],[Nivel Probabilidad]] -> 6 | R14: =IF(Q14>=6,"Alto", IF(Q14>=3,"Medio","Bajo")) -> Alto | S14: Presupuesto de potencia con margen ≥25%
K15: =Tabla_SR[[#This Row],[ID]] -> SR-16 | L15: =Tabla_SR[[#This Row],[Descripción del Requerimiento]] -> El sistema deberá cumplir con requisitos de EMI/EMC compatibles con operación satelital, evitando interferencias internas y externas durante todo el proceso de lanzamiento, despliege y operación. | M15: =Tabla_SR[[#This Row],[Riesgo]] -> Alto | N15: 15 | O15: =_xlfn.XLOOKUP(M15, Tabla5[Impacto], Tabla5[Nivel]) -> 3 | P15: =IF(N15<=10,1, IF(N15<=30,2,3)) -> 2 | Q15: =Tabla710[[#This Row],[Nivel Impacto]]*Tabla710[[#This Row],[Nivel Probabilidad]] -> 6 | R15: =IF(Q15>=6,"Alto", IF(Q15>=3,"Medio","Bajo")) -> Alto | S15: Revisión de layout 3D y mockup mecánico
K16: =Tabla_SR[[#This Row],[ID]] -> SR-17 | L16: =Tabla_SR[[#This Row],[Descripción del Requerimiento]] -> El sistema deberá diseñarse de forma modular y permitir la actualización de firmware en vuelo (OTA). | M16: =Tabla_SR[[#This Row],[Riesgo]] -> Bajo | N16: 10 | O16: =_xlfn.XLOOKUP(M16, Tabla5[Impacto], Tabla5[Nivel]) -> 1 | P16: =IF(N16<=10,1, IF(N16<=30,2,3)) -> 1 | Q16: =Tabla710[[#This Row],[Nivel Impacto]]*Tabla710[[#This Row],[Nivel Probabilidad]] -> 1 | R16: =IF(Q16>=6,"Alto", IF(Q16>=3,"Medio","Bajo")) -> Bajo | S16: Simulaciones CAD para estimaciones de masas y revisión periodica de masa en el prototipo
K17: =Tabla_SR[[#This Row],[ID]] -> SR-18 | L17: =Tabla_SR[[#This Row],[Descripción del Requerimiento]] -> El sistema deberá certificarse mediante prueba térmo-vacio, mecánicas, EMI y eléctricas en las instalaciones de Centro Espacial Nacional y ser validado en órbita. | M17: =Tabla_SR[[#This Row],[Riesgo]] -> Bajo | N17: 20 | O17: =_xlfn.XLOOKUP(M17, Tabla5[Impacto], Tabla5[Nivel]) -> 1 | P17: =IF(N17<=10,1, IF(N17<=30,2,3)) -> 2 | Q17: =Tabla710[[#This Row],[Nivel Impacto]]*Tabla710[[#This Row],[Nivel Probabilidad]] -> 2 | R17: =IF(Q17>=6,"Alto", IF(Q17>=3,"Medio","Bajo")) -> Bajo | S17: Mediciones EMI/EMC y separación RF
K18: =Tabla_SR[[#This Row],[ID]] -> SR-19 | L18: =Tabla_SR[[#This Row],[Descripción del Requerimiento]] -> El sistema deberá ser respetar la envolvente interna permita, los volúmen prohibídos y las restricciones sobre protrusiones, mecanismos móviles y bordes activos, asegurando la integración con la plataforma. | M18: =Tabla_SR[[#This Row],[Riesgo]] -> 0 | N18: 10 | O18: =_xlfn.XLOOKUP(M18, Tabla5[Impacto], Tabla5[Nivel]) -> #N/A | P18: =IF(N18<=10,1, IF(N18<=30,2,3)) -> 1 | Q18: =Tabla710[[#This Row],[Nivel Impacto]]*Tabla710[[#This Row],[Nivel Probabilidad]] -> #N/A | R18: =IF(Q18>=6,"Alto", IF(Q18>=3,"Medio","Bajo")) -> #N/A
K19: =Tabla_SR[[#This Row],[ID]] -> SR-20 | L19: =Tabla_SR[[#This Row],[Descripción del Requerimiento]] -> El sistema deberá soportar los ambientes mecánicos de lanzamiento (cargas cuasiestáticas, vibración y shock) definidos por el lanzador y deployer seleccionados. | M19: =Tabla_SR[[#This Row],[Riesgo]] -> 0 | N19: 10 | O19: =_xlfn.XLOOKUP(M19, Tabla5[Impacto], Tabla5[Nivel]) -> #N/A | P19: =IF(N19<=10,1, IF(N19<=30,2,3)) -> 1 | Q19: =Tabla710[[#This Row],[Nivel Impacto]]*Tabla710[[#This Row],[Nivel Probabilidad]] -> #N/A | R19: =IF(Q19>=6,"Alto", IF(Q19>=3,"Medio","Bajo")) -> #N/A
K20: =Tabla_SR[[#This Row],[ID]] -> SR-21 | L20: =Tabla_SR[[#This Row],[Descripción del Requerimiento]] -> El sistema deberá implementar Watchdog Timers externos e independientes para reinicio ante eventos SEU/Latch-up. | M20: =Tabla_SR[[#This Row],[Riesgo]] -> 0 | N20: 0 | O20: =_xlfn.XLOOKUP(M20, Tabla5[Impacto], Tabla5[Nivel]) -> #N/A | P20: =IF(N20<=10,1, IF(N20<=30,2,3)) -> 1 | Q20: =Tabla710[[#This Row],[Nivel Impacto]]*Tabla710[[#This Row],[Nivel Probabilidad]] -> #N/A | R20: =IF(Q20>=6,"Alto", IF(Q20>=3,"Medio","Bajo")) -> #N/A
K21: =Tabla_SR[[#This Row],[ID]] -> SR-22 | L21: =Tabla_SR[[#This Row],[Descripción del Requerimiento]] -> Protección electrónica contra Single Event Latch-up (SEL) mediante limitación de corriente activa. | M21: =Tabla_SR[[#This Row],[Riesgo]] -> 0 | N21: 0 | O21: =_xlfn.XLOOKUP(M21, Tabla5[Impacto], Tabla5[Nivel]) -> #N/A | P21: =IF(N21<=10,1, IF(N21<=30,2,3)) -> 1 | Q21: =Tabla710[[#This Row],[Nivel Impacto]]*Tabla710[[#This Row],[Nivel Probabilidad]] -> #N/A | R21: =IF(Q21>=6,"Alto", IF(Q21>=3,"Medio","Bajo")) -> #N/A
K22: =Tabla_SR[[#This Row],[ID]] -> SR-23 | L22: =Tabla_SR[[#This Row],[Descripción del Requerimiento]] -> Los componentes y materiales no metálicos que uitlice el sistema deberán cumplir con un TML < 1.0% y un CVCM <0.1% | M22: =Tabla_SR[[#This Row],[Riesgo]] -> 0 | N22: 0 | O22: =_xlfn.XLOOKUP(M22, Tabla5[Impacto], Tabla5[Nivel]) -> #N/A | P22: =IF(N22<=10,1, IF(N22<=30,2,3)) -> 1 | Q22: =Tabla710[[#This Row],[Nivel Impacto]]*Tabla710[[#This Row],[Nivel Probabilidad]] -> #N/A | R22: =IF(Q22>=6,"Alto", IF(Q22>=3,"Medio","Bajo")) -> #N/A

Sheet TEST
A1: ID | B1: Versión | C1: Nombre de la prueba | D1: Descripción del Requerimiento
A2: FUN-01 | B2: 1.0 | C2: Caracterización de Potencia | D2: Medición de consumo de corriente en todos los modos (Sleep, RX, Processing, TX Interface). Verificación de picos de arranque (Inrush Current).
A3: FUN-02 | B3: 1.0 | C3: Sensibilidad y Selectividad RF | D3: Verificación del umbral de recepción (-115 dBm estimado) y ancho de banda en 401-403 MHz usando generador de señales.
A4: FUN-03 | B4: 1.0 | C4: Simulación de Efecto Doppler | D4: Inyección de señales con desplazamiento de frecuencia variable (±10 kHz) para validar el algoritmo de corrección del receptor.
A5: FUN-04 | B5: 1.0 | C5: Integridad de Datos (BER) | D5: Transmisión de 1 millón de paquetes y verificación de tasa de error de bit (BER) y corrección CRC tras almacenamiento.
A6: FUN-05 | B6: 1.0 | C6: Interfaz CAN Bus & CSP | D6: Validación de intercambio de comandos y telemetría con emulador de OBC (o OBC real). Verificación de manejo de errores de bus.
A7: FUN-06 | B7: 1.0 | C7: Prueba de Watchdog y Failsafe | D7: Inyección de fallos de software y hardware (reset forzado) para medir tiempo de recuperación y estado seguro.
A8: FUN-07 | B8: 1.0 | C8: Actualización de Firmware OTA | D8: Simulación de carga de nueva imagen de software a través del bus de datos y verificación de checksum e instalación.
A9: THR-01 | B9: 1.0 | C9: Ciclado Térmico (Presión Ambiente) | D9: Ciclos de temperatura entre -30°C y +70°C en cámara climática para detectar fallas de soldadura o componentes infantiles (Stress screening).
A10: THR-02 | B10: 1.0 | C10: Vacío Térmico (TVAC) - Bake-out | D10: Exposición a alto vacío (<10⁻⁵ Torr) y temperatura elevada (+60°C) para desgasificación (Outgassing) y limpieza.
A11: THR-03 | B11: 1.0 | C11: Balance Térmico en Vacío | D11: Validación del modelo térmico: verificación de temperaturas de operación en vacío (solo conducción) en casos fríos y calientes.
A12: MEC-01 | B12: 1.0 | C12: Propiedades de Masa | D12: Medición precisa de masa total (< 3kg) y determinación del Centro de Gravedad (CoG) y Momentos de Inercia (MoI).
... A20: EMC-04 | B20: 1.0 | C20: Auto-Compatibilidad | D20: Verificación de que la transmisión UHF propia no resetea la CPU ni afecta sensores cercanos.
